pip_hdl/__init__.py
pip_hdl/cli.py
pip_hdl/graph.py
pip_hdl/metainfo.py
pip_hdl/template.py
pip_hdl/version.py
pip_hdl-0.3.0.dist-info/LICENSE
pip_hdl-0.3.0.dist-info/METADATA
pip_hdl-0.3.0.dist-info/WHEEL
pip_hdl-0.3.0.dist-info/entry_points.txt
pip_hdl-0.3.0.dist-info/RECORD
