Metadata-Version: 2.1
Name: pip-hdl
Version: 0.3.0
Summary: Tool to enable package managing for HDL VIP or IP cores (Verilog, SystemVerilog, VHDL) using Python pip
Home-page: https://github.com/esynr3z/pip-hdl
License: MIT
Author: esynr3z
Author-email: esynr3z@gmail.com
Requires-Python: >=3.8.1,<4.0.0
Classifier: License :: OSI Approved :: MIT License
Classifier: Programming Language :: Python :: 3
Classifier: Programming Language :: Python :: 3.9
Classifier: Programming Language :: Python :: 3.10
Classifier: Programming Language :: Python :: 3.11
Classifier: Programming Language :: Python :: 3.12
Requires-Dist: graphviz (>=0.20.1,<0.21.0)
Project-URL: Repository, https://github.com/esynr3z/pip-hdl
